<?xml version="1.0" encoding="UTF-8" standalone="yes"?>
<sst xmlns="http://schemas.openxmlformats.org/spreadsheetml/2006/main" count="433" uniqueCount="112"><si><t>tblinkfld_id</t></si><si><t>tblink_code</t></si><si><t>pobject_code_tbl_dest</t></si><si><t>処理順序</t></si><si><t>pobject_code_fld</t></si><si><t>tblinkfld_rubycode</t></si><si><t>tblinkfld_contents</t></si><si><t>pobject_code_tbl</t></si><si><t>tblinkfld_remark</t></si><si><t>tblinkfld_expiredate</t></si><si><t>blktbsfieldcode_contents</t></si><si><t>tblink_seqno</t></si><si><t>tblink_beforeafter</t></si><si><t>fieldcode_ftype</t></si><si><t>tblinkfld_update_ip</t></si><si><t>tblinkfld_created_at</t></si><si><t>tblinkfld_updated_at</t></si><si><t>updperson_name_upd</t></si><si><t>fieldcode_contents</t></si><si><t>updperson_code_upd</t></si><si><t>puracts</t></si><si><t>contents</t></si><si><t xml:space="preserve">auto created </t></si><si><t>2099/12/31</t></si><si><t>undefined</t></si><si><t>self</t></si><si><t>varchar2</t></si><si><t>2015/03/14 10:40</t></si><si><t>system</t></si><si><t>id</t></si><si><t>number</t></si><si><t>127.0.0.1</t></si><si><t>2015/05/28 20:53</t></si><si><t>各テーブルのユニークkey
各テーブルに必ず一つ必要
viewのとき　テーブル名.chop_idとしも存在する。</t></si><si><t>remark</t></si><si><t>システムがセットする備考</t></si><si><t>expiredate</t></si><si><t>date</t></si><si><t>有効日</t></si><si><t>update_ip</t></si><si><t>created_at</t></si><si><t>timestamp(6)</t></si><si><t>updated_at</t></si><si><t>persons_id_upd</t></si><si><t>qty</t></si><si><t>price</t></si><si><t>2015/04/02 19:38</t></si><si><t>amt</t></si><si><t>2015/05/08 23:11</t></si><si><t>sno</t></si><si><t>オーダに対する実績
sno_instは回答納期、又は相手先からのｋｅｙになるのでsno_ordに変更
必須項目</t></si><si><t>2015/06/01 21:12</t></si><si><t>テーブル毎にシステムでユニークにする番号
id.to_sをsnoにすることを基本としている。
追加には、自動的にindexを作製するが、削除は対応してない。</t></si><si><t>isudate</t></si><si><t>受入、入力日</t></si><si><t>2015/03/28 14:04</t></si><si><t>発行日</t></si><si><t>rcptdate</t></si><si><t>受入日
完成日　完成して該当部署で受け取った日</t></si><si><t>locas_id_to</t></si><si><t>2015/06/05 01:06</t></si><si><t>tax</t></si><si><t>2015/05/19 22:03</t></si><si><t>qty_case</t></si><si><t>sno_ord</t></si><si><t>2015/07/20 22:05</t></si><si><t>instsの元のテーブルxxxordsのsno</t></si><si><t>manual</t></si><si><t>char</t></si><si><t>m:手動又はa:自動</t></si><si><t>contract_price</t></si><si><t>画面から入力された時　"Z"をセット
rule_price="1"(画面からの入力可)が条件</t></si><si><t>2015/04/04 10:18</t></si><si><t>単価契約フラグ
1:発注日ベース　2:納期ベース　3:受入日ベース   4:出荷日ベース　5:検収ベース  
7:出荷日までに決定する単価　8:受入日までに決定する単価　
9:単価決定=検収日
X:社内単価未定</t></si><si><t>gno</t></si><si><t>2015/07/20 15:12</t></si><si><t>注文単位別key  ユニーク性は保証されない。 
一枚の注文書に複数の品目がある時、その注文書の識別key</t></si><si><t>gno_lineno</t></si><si><t>re_deliver_f</t></si><si><t>2015/03/22 21:25</t></si><si><t>1:再納品　　既に支払済、又は請求済(入金済)</t></si><si><t>dealers_id</t></si><si><t>prjnos_id</t></si><si><t>cno</t></si><si><t>得意先、業者、又は作業現場からのｋｅｙ</t></si><si><t>opeitms_id</t></si><si><t>itms_id_pare</t></si><si><t>processseq_pare</t></si><si><t>同一item_coseに複数の作業工程がある時の順番
stkhistsの工程毎の在庫場所を示すためのkey
999が最終工程になる。</t></si><si><t>chrgs_id</t></si><si><t>2015/04/12 02:52</t></si><si><t>cno_inst</t></si><si><t>2015/07/11 09:20</t></si><si><t xml:space="preserve">command_c[:id] = proc_get_nextval("puracts_seq") </t><phoneticPr fontId="2"/></si><si><t>(@result_isudate)</t><phoneticPr fontId="2"/></si><si><t>(@result_rcptdate)</t><phoneticPr fontId="2"/></si><si><t>(@purinst_opeitm_id)</t><phoneticPr fontId="2"/></si><si><t>(@result_qty_case)</t><phoneticPr fontId="2"/></si><si><t>(@result_qty)</t><phoneticPr fontId="2"/></si><si><t>@purinst_sno_ord</t><phoneticPr fontId="2"/></si><si><t>(@result_gno)</t><phoneticPr fontId="2"/></si><si><t>(@result_gno_lineno)</t><phoneticPr fontId="2"/></si><si><t>(@purinst_prjno_id)</t><phoneticPr fontId="2"/></si><si><t>(@purinst_cno)</t><phoneticPr fontId="2"/></si><si><t>(@result_cno)</t><phoneticPr fontId="2"/></si><si><t>(@purinst_itm_id_pare)</t><phoneticPr fontId="2"/></si><si><t>proc_tblink_r_results_puracts_self10</t><phoneticPr fontId="2"/></si><si><t>(@purinst_dealer_id)</t><phoneticPr fontId="2"/></si><si><t>(@purinst_chrg_id)</t><phoneticPr fontId="2"/></si><si><t>(@purinst_loca_id_to)</t><phoneticPr fontId="2"/></si><si><t>(@purinst_processseq_pare)</t><phoneticPr fontId="2"/></si><si><t>(
itm_rec = proc_get_viewrec_from_id("opeitms",command_c[:puract_opeitm_id])
dealer_rec = proc_get_viewrec_from_id("dealers",command_c[:puract_dealer_id])
command_c[:itm_code] = itm_rec["itm_code"]
command_c[:loca_code_dealer] = dealer_rec["loca_code_dealer"]
getprice = proc_price_amt(command_c)
getprice[:price].to_f
)</t><phoneticPr fontId="2"/></si></sst>