<?xml version="1.0" encoding="UTF-8" standalone="yes"?>
<sst xmlns="http://schemas.openxmlformats.org/spreadsheetml/2006/main" count="491" uniqueCount="126"><si><t>opeitm_id</t></si><si><t>itm_code</t></si><si><t>itm_name</t></si><si><t>作業優先順位</t></si><si><t>作業順序</t></si><si><t>loca_code</t></si><si><t>loca_name</t></si><si><t>opeitm_prdpurshp</t></si><si><t>opeitm_operation</t></si><si><t>opeitm_packqty</t></si><si><t>unit_code_case</t></si><si><t>unit_name_case</t></si><si><t>opeitm_parenum</t></si><si><t>opeitm_chilnum</t></si><si><t>opeitm_minqty</t></si><si><t>opeitm_maxqty</t></si><si><t>opeitm_safestkqty</t></si><si><t>opeitm_shuffle_flg</t></si><si><t>opeitm_shuffle_loca</t></si><si><t>opeitm_chkord</t></si><si><t>opeitm_stktaking_f</t></si><si><t>opeitm_chkord_prc</t></si><si><t>opeitm_rule_price</t></si><si><t>opeitm_esttosch</t></si><si><t>opeitm_chkinst</t></si><si><t>opeitm_mold</t></si><si><t>boxe_code</t></si><si><t>boxe_name</t></si><si><t>opeitm_units_lttime</t></si><si><t>LT</t></si><si><t>opeitm_consumtype</t></si><si><t>opeitm_autocreate_ord</t></si><si><t>opeitm_autocreate_inst</t></si><si><t>opeitm_autocreate_act</t></si><si><t>opeitm_opt_fixoterm</t></si><si><t>opeitm_contents</t></si><si><t>opeitm_remark</t></si><si><t>opeitm_expiredate</t></si><si><t>opeitm_packno_flg</t></si><si><t>opeitm_opt_fix_flg</t></si><si><t>unit_name</t></si><si><t>unit_name_outbox</t></si><si><t>person_name_upd</t></si><si><t>opeitm_updated_at</t></si><si><t>unit_name_box</t></si><si><t>opeitm_update_ip</t></si><si><t>opeitm_created_at</t></si><si><t>itm_deth</t></si><si><t>itm_expiredate</t></si><si><t>unit_code</t></si><si><t>unit_code_box</t></si><si><t>unit_code_outbox</t></si><si><t>person_code_upd</t></si><si><t>opeitm_prjalloc_flg</t></si><si><t>ITEM2001</t></si><si><t>部品2001</t></si><si><t>parts_wh</t></si><si><t>部品置場</t></si><si><t>shp</t></si><si><t>出庫</t></si><si><t>PCS</t></si><si><t>個</t></si><si><t>dummy</t></si><si><t>特に指定せず</t></si><si><t>2099/12/31</t></si><si><t>system</t></si><si><t>2016/06/26 17:31</t></si><si><t>127.0.0.1</t></si><si><t>2013/10/27 11:19</t></si><si><t>ITEM3367</t></si><si><t>部品3367</t></si><si><t>2016/02/21 23:55</t></si><si><t>ITEM3374</t></si><si><t>部品3374</t></si><si><t>2016/03/26 21:00</t></si><si><t>2099/01/30</t></si><si><t>ITEM2002</t></si><si><t>部品2002</t></si><si><t>2016/03/26 22:01</t></si><si><t>ITEM3371</t></si><si><t>部品3371</t></si><si><t>2016/03/27 15:59</t></si><si><t>ITEM3372</t></si><si><t>部品3372</t></si><si><t>2016/03/27 16:04</t></si><si><t>2099/01/01</t></si><si><t>ITEM3380</t></si><si><t>部品3380</t></si><si><t>2016/03/27 16:12</t></si><si><t>ITEM3381</t></si><si><t>部品3381</t></si><si><t>2016/03/27 16:27</t></si><si><t>ITEM3383</t></si><si><t>部品3383</t></si><si><t>2016/03/27 16:36</t></si><si><t>ITEM3384</t></si><si><t>部品3384</t></si><si><t>2016/03/27 16:41</t></si><si><t>ITEM3386</t></si><si><t>部品3386</t></si><si><t>2016/03/27 17:18</t></si><si><t>ITEM3390</t></si><si><t>部品3390</t></si><si><t>2016/03/29 21:59</t></si><si><t>ITEM3391</t></si><si><t>部品3391</t></si><si><t>2016/03/29 23:16</t></si><si><t>ITEM5002</t></si><si><t>部品5002</t></si><si><t>2014/06/25 21:36</t></si><si><t>ITEM3382</t></si><si><t>部品3382</t></si><si><t>2016/03/27 16:33</t></si><si><t>ITEM3385</t></si><si><t>部品3385</t></si><si><t>2016/03/29 21:35</t></si><si><t>ITEM3387</t></si><si><t>部品3387</t></si><si><t>2016/03/29 21:38</t></si><si><t>ITEM3389</t></si><si><t>部品3389</t></si><si><t>2016/03/29 21:54</t></si><si><t>ITEM3392</t></si><si><t>部品3392</t></si><si><t>2016/03/29 23:19</t></si><si><t>con</t><phoneticPr fontId="2"/></si></sst>